setup.cfg
setup.py
osex/__init__.py
osex/locate.py
osex.egg-info/PKG-INFO
osex.egg-info/SOURCES.txt
osex.egg-info/dependency_links.txt
osex.egg-info/requires.txt
osex.egg-info/top_level.txt
scripts/renames
scripts/select-locate
scripts/symlink