Metadata-Version: 1.1
Name: osex
Version: 0.3.2
Summary: extension for python's build-in operating system interface
Home-page: https://github.com/fphammerle/osex
Author: Fabian Peter Hammerle
Author-email: fabian.hammerle@gmail.com
License: UNKNOWN
Download-URL: https://github.com/fphammerle/osex/tarball/0.3.2
Platform: UNKNOWN
